irspdf/__init__.py
irspdf/build.py
irspdf/ir_collection.py
irspdf/query.py
irspdf/update.py
irspdf-0.4.1.dist-info/METADATA
irspdf-0.4.1.dist-info/WHEEL
irspdf-0.4.1.dist-info/top_level.txt
irspdf-0.4.1.dist-info/RECORD
