Metadata-Version: 2.1
Name: irspdf
Version: 0.4.1
Summary: A simple information retrieval system for pdf documents
Home-page: UNKNOWN
Author: Jibril Frej
Author-email: <frejjibril@gmail.com>
License: UNKNOWN
Project-URL: Source code, https://github.com/Jibril-Frej/irspdf
Project-URL: Documentation, https://irspdf.readthedocs.io/en/latest/
Keywords: python,information retrieval
Platform: UNKNOWN
Classifier: Programming Language :: Python :: 3
Requires-Dist: numpy
Requires-Dist: pdfplumber
Requires-Dist: stop-words
Requires-Dist: snowballstemmer
